gbp_testkit/__init__.py
gbp_testkit/data/jenkins_build.json
gbp_testkit/data/job_parameters.json
gbp_testkit/data/logs.txt
gbp_testkit/factories.py
gbp_testkit/fixtures.py
gbp_testkit/helpers.py
gbp_testkit/py.typed
gbp_testkit/settings.py
gentoo_build_publisher-3.1.0.dist-info/METADATA
gentoo_build_publisher-3.1.0.dist-info/WHEEL
gentoo_build_publisher-3.1.0.dist-info/entry_points.txt
gentoo_build_publisher-3.1.0.dist-info/licenses/LICENSE
gentoo_build_publisher/__init__.py
gentoo_build_publisher/build_publisher.py
gentoo_build_publisher/checks.py
gentoo_build_publisher/cli/__init__.py
gentoo_build_publisher/cli/addmachine.py
gentoo_build_publisher/cli/addrepo.py
gentoo_build_publisher/cli/apikey.py
gentoo_build_publisher/cli/check.py
gentoo_build_publisher/cli/delete.py
gentoo_build_publisher/cli/utils.py
gentoo_build_publisher/cli/worker.py
gentoo_build_publisher/contrib/deployment/containers.conf
gentoo_build_publisher/contrib/deployment/gentoo-build-publisher-pre.service
gentoo_build_publisher/contrib/deployment/gentoo-build-publisher-worker.service
gentoo_build_publisher/contrib/deployment/gentoo-build-publisher-wsgi.service
gentoo_build_publisher/contrib/deployment/gentoo-build-publisher.conf
gentoo_build_publisher/contrib/deployment/nginx.conf
gentoo_build_publisher/contrib/deployment/project_template/manage.py-tpl
gentoo_build_publisher/contrib/deployment/project_template/project_name/__init__.py-tpl
gentoo_build_publisher/contrib/deployment/project_template/project_name/asgi.py-tpl
gentoo_build_publisher/contrib/deployment/project_template/project_name/settings.py-tpl
gentoo_build_publisher/contrib/deployment/project_template/project_name/wsgi.py-tpl
gentoo_build_publisher/contrib/deployment/rsyncd.conf
gentoo_build_publisher/django/__init__.py
gentoo_build_publisher/django/_setup.py
gentoo_build_publisher/django/gentoo_build_publisher/__init__.py
gentoo_build_publisher/django/gentoo_build_publisher/apps.py
gentoo_build_publisher/django/gentoo_build_publisher/migrations/0001_initial.py
gentoo_build_publisher/django/gentoo_build_publisher/migrations/0002_alter_buildmodel_number.py
gentoo_build_publisher-3.1.0.dist-info/RECORD
