Metadata-Version: 2.1
Name: gentoo-build-publisher
Version: 3.1.0
Summary: Gentoo Build Publisher
Author-Email: Albert Hopkins <marduk@letterboxes.org>
License: GPL3+
Classifier: Development Status :: 5 - Production/Stable
Classifier: Framework :: Django
Classifier: Intended Audience :: System Administrators
Classifier: License :: OSI Approved :: GNU General Public License v3 or later (GPLv3+)
Classifier: Operating System :: POSIX :: Linux
Classifier: Programming Language :: Python :: 3
Classifier: Topic :: System :: Operating System Kernels :: Linux
Classifier: Topic :: System :: Operating System
Classifier: Topic :: System :: Software Distribution
Classifier: Topic :: System :: Systems Administration
Project-URL: homepage, https://github.com/enku/gentoo-build-publisher
Project-URL: repository, https://github.com/enku/gentoo-build-publisher
Requires-Python: >=3.12
Requires-Dist: ariadne>=0.14.0
Requires-Dist: ariadne_django
Requires-Dist: celery[msgpack]
Requires-Dist: django
Requires-Dist: requests
Requires-Dist: yarl!=1.9.1
Requires-Dist: gbpcli>=3.0.0
Requires-Dist: orjson>=3.9.1
Requires-Dist: cryptography>=42.0.4
Requires-Dist: rich>=13.7.0
Requires-Dist: blinker>=1.9.0
Provides-Extra: redis
Requires-Dist: rq>=1.15.1; extra == "redis"
Provides-Extra: test
Requires-Dist: factory-boy>=3.3.3; extra == "test"
Requires-Dist: unittest-fixtures>=2.3.0; extra == "test"
